FPGA_Clk_Div/rtl/Baud_Clk_Divider_50.v
//============================================================
// Module Name : Baud_Clk_Divider_50
// Description : 50% duty-cycle clock divider for UART baud clock
//
// Function:
//   - Divides the input clock by 2*HALF_DIV.
//   - Output clock toggles every HALF_DIV input clock cycles.
//   - Uses a down-counter.
//   - Terminal count is detected using only ONE BIT:
//       wCntDec[CNT_W]
//     This bit becomes '1' when the counter underflows.
//
// Example:
//   If input clock = 10 MHz
//   HALF_DIV = 520
//
//   Output frequency:
//       Fout = 10 MHz / (2 * 520)
//            = 9615.38 Hz
//
// Notes:
//   - For a real 9600 baud UART from 10 MHz, exact integer division
//     is not possible.
//   - This divider gives a close baud clock with 50% duty cycle.
//============================================================

module Baud_Clk_Divider_50
#(
    parameter HALF_DIV = 520
)
(
    input  wire iClk,       // Input clock, for example slow_clk = 10 MHz
    input  wire iResetN,    // Asynchronous active-low reset
    output reg  oClk        // Divided output clock, 50% duty cycle
);

    //--------------------------------------------------------
    // Counter width calculation
    //
    // HALF_DIV+1 is used so the counter has enough bits
    // to hold the reload value and also detect underflow.
    //--------------------------------------------------------
    localparam CNT_W = $clog2(HALF_DIV + 1);

    //--------------------------------------------------------
    // Counter register
    //
    // rCnt is declared with one extra bit:
    //   [CNT_W:0]
    //
    // The extra MSB is used as the underflow indication bit.
    //--------------------------------------------------------
    reg [CNT_W:0] rCnt;

    //--------------------------------------------------------
    // Decremented counter value
    //
    // This wire calculates rCnt - 1 before loading the register.
    // The MSB of this result is used to detect underflow.
    //
    // This avoids using a wide comparator such as:
    //   if (rCnt == 0)
    //
    // Instead, only one bit is checked:
    //   if (wCntDec[CNT_W])
    //--------------------------------------------------------
    wire [CNT_W:0] wCntDec;

    assign wCntDec = rCnt - 1'b1;

    //--------------------------------------------------------
    // Clock divider logic
    //
    // Reset:
    //   - Load the counter with HALF_DIV-1.
    //   - Drive output clock low.
    //
    // Normal operation:
    //   - Counter counts down.
    //   - When underflow is detected, reload counter and toggle oClk.
    //--------------------------------------------------------
    always @(posedge iClk or negedge iResetN) begin
        if (!iResetN) begin
            rCnt <= HALF_DIV - 1'b1;
            oClk <= 1'b0;
        end
        else begin
            if (wCntDec[CNT_W]) begin
                rCnt <= HALF_DIV - 1'b1;
                oClk <= ~oClk;
            end
            else begin
                rCnt <= wCntDec;
            end
        end
    end

endmodule

FPGA_UART/rtl/UART_Tx_16bit.v
//============================================================
// File        : UART_Tx_16bit.v
// Module      : UART_Tx_16bit
// Description : UART transmitter for 16-bit FIFO data
//
// UART Frame:
//   Start bit : 0
//   Data bits : 16 bits, LSB first
//   Stop bit  : 1
//
// Baud generation:
//   - Uses Baud_Clk_Divider_50 internally.
//   - The divided baud clock is edge-detected.
//   - The FSM advances once per baud period.
//
// FSM encoding:
//   IDLE  = 0
//   START = 1
//   DATA  = 2
//   STOP  = 4
//============================================================

module UART_Tx_16bit
#(
    parameter integer BAUD_HALF_DIV = 520
)
(
    input  wire        iSlowClk,      // slow clock, for example 10 MHz
    input  wire        iResetN,       // async active-low reset

    input  wire        iFifoEmpty,    // connected to FIFO rempty
    input  wire [15:0] iFifoData,     // connected to FIFO rdata[15:0]

    output reg         oFifoRinc,     // FIFO read increment pulse
    output reg         oSerialTx,     // UART serial output
    output reg         oBusyTx        // UART busy indication
);

    //--------------------------------------------------------
    // Internal baud clock divider
    //--------------------------------------------------------
    wire wBaudClk;

    Baud_Clk_Divider_50
    #(
        .HALF_DIV(BAUD_HALF_DIV)
    )
    u_Baud_Clk_Divider_50
    (
        .iClk    (iSlowClk),
        .iResetN (iResetN),
        .oClk    (wBaudClk)
    );

    //--------------------------------------------------------
    // Baud clock rising-edge detector
    //
    // wBaudStep is a one-cycle enable pulse in iSlowClk domain.
    //--------------------------------------------------------
    reg rBaudClkD;

    wire wBaudStep;
    assign wBaudStep = wBaudClk & ~rBaudClkD;

    //--------------------------------------------------------
    // FSM encoding: 0, 1, 2, 4
    //--------------------------------------------------------
    localparam [2:0] ST_IDLE  = 3'b000;
    localparam [2:0] ST_START = 3'b001;
    localparam [2:0] ST_DATA  = 3'b010;
    localparam [2:0] ST_STOP  = 3'b100;

    reg [2:0] rState;

    //--------------------------------------------------------
    // Internal registers
    //--------------------------------------------------------
    reg [15:0] rTxShift;       // data shift register
    reg [4:0]  rBitCnt;        // counts transmitted data bits
    reg        rStopStarted;   // used to hold stop bit for one baud period

    //--------------------------------------------------------
    // UART transmitter logic
    //--------------------------------------------------------
    always @(posedge iSlowClk or negedge iResetN) begin
        if (!iResetN) begin
            rBaudClkD    <= 1'b0;
            rState       <= ST_IDLE;
            rTxShift     <= 16'd0;
            rBitCnt      <= 5'd0;
            rStopStarted <= 1'b0;

            oFifoRinc    <= 1'b0;
            oSerialTx    <= 1'b1;     // UART idle line is high
            oBusyTx      <= 1'b0;
        end
        else begin
            //------------------------------------------------
            // Register baud clock for edge detection
            //------------------------------------------------
            rBaudClkD <= wBaudClk;

            //------------------------------------------------
            // Default value: FIFO read pulse is one slow_clk cycle
            //------------------------------------------------
            oFifoRinc <= 1'b0;

            //------------------------------------------------
            // FSM advances only once per baud period
            //------------------------------------------------
            if (wBaudStep) begin

                case (rState)

                    //------------------------------------------------
                    // IDLE:
                    // Wait until FIFO has data.
                    //------------------------------------------------
                    ST_IDLE: begin
                        oSerialTx    <= 1'b1;
                        oBusyTx      <= 1'b0;
                        rBitCnt      <= 5'd0;
                        rStopStarted <= 1'b0;

                        if (!iFifoEmpty) begin
                            rTxShift  <= iFifoData;
                            oFifoRinc <= 1'b1;

                            //------------------------------------------------
                            // Start bit begins now
                            //------------------------------------------------
                            oSerialTx <= 1'b0;
                            oBusyTx   <= 1'b1;
                            rState    <= ST_START;
                        end
                    end

                    //------------------------------------------------
                    // START:
                    // Start bit has lasted one baud period.
                    // Now transmit data bit 0.
                    //------------------------------------------------
                    ST_START: begin
                        oSerialTx <= rTxShift[0];
                        rTxShift  <= {1'b0, rTxShift[15:1]};
                        rBitCnt   <= 5'd1;
                        rState    <= ST_DATA;
                    end

                    //------------------------------------------------
                    // DATA:
                    // Transmit data bits 1 to 15.
                    //------------------------------------------------
                    ST_DATA: begin
                        oSerialTx <= rTxShift[0];
                        rTxShift  <= {1'b0, rTxShift[15:1]};

                        if (rBitCnt == 5'd15) begin
                            rState <= ST_STOP;
                        end

                        rBitCnt <= rBitCnt + 1'b1;
                    end

                    //------------------------------------------------
                    // STOP:
                    // First baud step: drive stop bit high.
                    // Second baud step: stop bit completed, go IDLE.
                    //------------------------------------------------
                    ST_STOP: begin
                        if (!rStopStarted) begin
                            oSerialTx    <= 1'b1;
                            rStopStarted <= 1'b1;
                        end
                        else begin
                            oSerialTx    <= 1'b1;
                            oBusyTx      <= 1'b0;
                            rStopStarted <= 1'b0;
                            rBitCnt      <= 5'd0;
                            rState       <= ST_IDLE;
                        end
                    end

                    default: begin
                        rState       <= ST_IDLE;
                        oSerialTx    <= 1'b1;
                        oBusyTx      <= 1'b0;
                        rStopStarted <= 1'b0;
                    end

                endcase
            end
        end
    end

endmodule

FPGA_UART/rtl/TB_UART_Tx_16bit_With_Divider.v
`timescale 1ns/1ps

//============================================================
// File        : TB_UART_Tx_16bit_With_Divider.v
// Testbench   : TB_UART_Tx_16bit_With_Divider
// Description : Testbench for UART_Tx_16bit
//
// The UART module internally instantiates Baud_Clk_Divider_50.
//
// Test scenario:
//   1. Generate 10 MHz slow clock.
//   2. Reset the design.
//   3. Send first FIFO word: 16'hA55A.
//   4. Check UART frame:
//        Start + 16 data bits LSB first + Stop
//   5. Send second FIFO word: 16'h1234.
//   6. Dump VCD file for ModelSim waveform analysis.
//============================================================

module TB_UART_Tx_16bit_With_Divider;

    //--------------------------------------------------------
    // Testbench parameters
    //
    // For simulation speed:
    //   BAUD_HALF_DIV_TB = 5
    //
    // In the real project with 10 MHz slow clock:
    //   BAUD_HALF_DIV = 520
    //--------------------------------------------------------
    localparam integer BAUD_HALF_DIV_TB = 5;
    localparam integer BAUD_PERIOD_CLKS = 2 * BAUD_HALF_DIV_TB;

    //--------------------------------------------------------
    // Testbench signals
    //--------------------------------------------------------
    reg        iSlowClk;
    reg        iResetN;

    reg        iFifoEmpty;
    reg [15:0] iFifoData;

    wire       oFifoRinc;
    wire       oSerialTx;
    wire       oBusyTx;

    //--------------------------------------------------------
    // DUT instantiation
    //--------------------------------------------------------
    UART_Tx_16bit
    #(
        .BAUD_HALF_DIV(BAUD_HALF_DIV_TB)
    )
    dut
    (
        .iSlowClk   (iSlowClk),
        .iResetN    (iResetN),

        .iFifoEmpty (iFifoEmpty),
        .iFifoData  (iFifoData),

        .oFifoRinc  (oFifoRinc),
        .oSerialTx  (oSerialTx),
        .oBusyTx    (oBusyTx)
    );

    //--------------------------------------------------------
    // 10 MHz slow clock generation
    //
    // Period = 100 ns
    //--------------------------------------------------------
    initial begin
        iSlowClk = 1'b0;
        forever #50 iSlowClk = ~iSlowClk;
    end

    //--------------------------------------------------------
    // Wait one UART bit period
    //--------------------------------------------------------
    task Wait_Baud_Period;
        begin
            repeat (BAUD_PERIOD_CLKS) @(posedge iSlowClk);
            #1;
        end
    endtask

    //--------------------------------------------------------
    // Drive one FIFO word
    //--------------------------------------------------------
    task Drive_Fifo_Word;
        input [15:0] data_word;
        begin
            @(posedge iSlowClk);
            iFifoData  <= data_word;
            iFifoEmpty <= 1'b0;

            //------------------------------------------------
            // Wait until UART reads the FIFO
            //------------------------------------------------
            wait (oFifoRinc == 1'b1);

            @(posedge iSlowClk);
            iFifoEmpty <= 1'b1;
        end
    endtask

    //--------------------------------------------------------
    // Check UART serial frame
    //
    // Expected order:
    //   bit 0  = start bit = 0
    //   bit 1  = data[0]
    //   bit 2  = data[1]
    //   ...
    //   bit 16 = data[15]
    //   bit 17 = stop bit = 1
    //--------------------------------------------------------
    task Check_UART_Frame;
        input [15:0] data_word;

        reg [17:0] expected_frame;
        integer bit_index;

        begin
            expected_frame = {1'b1, data_word, 1'b0};

            //------------------------------------------------
            // Start checking when FIFO read occurs.
            // At this moment, start bit should already be driven.
            //------------------------------------------------
            wait (oFifoRinc == 1'b1);
            #1;

            for (bit_index = 0; bit_index < 18; bit_index = bit_index + 1) begin
                if (oSerialTx !== expected_frame[bit_index]) begin
                    $display("ERROR at time %0t: UART bit %0d mismatch. Expected=%0b, Got=%0b",
                             $time, bit_index, expected_frame[bit_index], oSerialTx);
                end
                else begin
                    $display("PASS  at time %0t: UART bit %0d = %0b",
                             $time, bit_index, oSerialTx);
                end

                Wait_Baud_Period();
            end
        end
    endtask

    //--------------------------------------------------------
    // Main stimulus
    //--------------------------------------------------------
    initial begin
        //----------------------------------------------------
        // VCD dump for waveform viewing
        //----------------------------------------------------
        $dumpfile("TB_UART_Tx_16bit_With_Divider.vcd");
        $dumpvars(0, TB_UART_Tx_16bit_With_Divider);

        //----------------------------------------------------
        // Initial values
        //----------------------------------------------------
        iResetN    = 1'b0;
        iFifoEmpty = 1'b1;
        iFifoData  = 16'h0000;

        //----------------------------------------------------
        // Reset
        //----------------------------------------------------
        repeat (5) @(posedge iSlowClk);
        iResetN = 1'b1;

        repeat (20) @(posedge iSlowClk);

        //----------------------------------------------------
        // First word test
        //----------------------------------------------------
        fork
            Drive_Fifo_Word(16'hA55A);
            Check_UART_Frame(16'hA55A);
        join

        //----------------------------------------------------
        // Wait until UART is fully idle
        //----------------------------------------------------
        wait (oBusyTx == 1'b0);
        repeat (20) @(posedge iSlowClk);

        //----------------------------------------------------
        // Second word test
        //----------------------------------------------------
        fork
            Drive_Fifo_Word(16'h1234);
            Check_UART_Frame(16'h1234);
        join

        wait (oBusyTx == 1'b0);
        repeat (20) @(posedge iSlowClk);

        $display("UART testbench finished.");
        $finish;
    end

endmodule

FPGA_UART/sim/TB_UART_Tx_16bit_With_Divider.vcd
$date
	Fri Jun 26 15:20:43 2026
$end
$version
	ModelSim Version 2020.1
$end
$timescale
	1ps
$end

$scope module TB_UART_Tx_16bit_With_Divider $end
$var parameter 32 ! BAUD_HALF_DIV_TB $end
$var parameter 32 " BAUD_PERIOD_CLKS $end
$var reg 1 # iSlowClk $end
$var reg 1 $ iResetN $end
$var reg 1 % iFifoEmpty $end
$var reg 16 & iFifoData [15:0] $end
$var wire 1 ' oFifoRinc $end
$var wire 1 ( oSerialTx $end
$var wire 1 ) oBusyTx $end

$scope task Wait_Baud_Period $end
$upscope $end

$scope task Drive_Fifo_Word $end
$var reg 16 * data_word [15:0] $end
$upscope $end

$scope task Check_UART_Frame $end
$var reg 16 + data_word [15:0] $end
$var reg 18 , expected_frame [17:0] $end
$var integer 32 - bit_index $end
$upscope $end

$scope module dut $end
$var parameter 32 . BAUD_HALF_DIV $end
$var parameter 3 / ST_IDLE $end
$var parameter 3 0 ST_START $end
$var parameter 3 1 ST_DATA $end
$var parameter 3 2 ST_STOP $end
$var wire 1 3 iSlowClk $end
$var wire 1 4 iResetN $end
$var wire 1 5 iFifoEmpty $end
$var wire 1 6 iFifoData [15] $end
$var wire 1 7 iFifoData [14] $end
$var wire 1 8 iFifoData [13] $end
$var wire 1 9 iFifoData [12] $end
$var wire 1 : iFifoData [11] $end
$var wire 1 ; iFifoData [10] $end
$var wire 1 < iFifoData [9] $end
$var wire 1 = iFifoData [8] $end
$var wire 1 > iFifoData [7] $end
$var wire 1 ? iFifoData [6] $end
$var wire 1 @ iFifoData [5] $end
$var wire 1 A iFifoData [4] $end
$var wire 1 B iFifoData [3] $end
$var wire 1 C iFifoData [2] $end
$var wire 1 D iFifoData [1] $end
$var wire 1 E iFifoData [0] $end
$var reg 1 F oFifoRinc $end
$var reg 1 G oSerialTx $end
$var reg 1 H oBusyTx $end
$var wire 1 I wBaudClk $end
$var reg 1 J rBaudClkD $end
$var wire 1 K wBaudStep $end
$var reg 3 L rState [2:0] $end
$var reg 16 M rTxShift [15:0] $end
$var reg 5 N rBitCnt [4:0] $end
$var reg 1 O rStopStarted $end

$scope module u_Baud_Clk_Divider_50 $end
$var parameter 32 P HALF_DIV $end
$var parameter 32 Q CNT_W $end
$var wire 1 3 iClk $end
$var wire 1 4 iResetN $end
$var reg 1 R oClk $end
$var reg 4 S rCnt [3:0] $end
$var wire 1 T wCntDec [3] $end
$var wire 1 U wCntDec [2] $end
$var wire 1 V wCntDec [1] $end
$var wire 1 W wCntDec [0] $end
$upscope $end
$upscope $end
$upscope $end
$enddefinitions $end
#0
$dumpvars
0#
0$
1%
b0 &
0F
1G
0H
0R
b100 S
0J
b0 L
b0 M
b0 N
0O
bx *
bx +
bx ,
b101 !
b1010 "
b101 .
b0 /
b1 0
b10 1
b100 2
b101 P
b11 Q
bx -
0'
1(
0)
0I
1W
1V
0U
0T
0K
0E
0D
0C
0B
0A
0@
0?
0>
0=
0<
0;
0:
09
08
07
06
15
04
03
$end
#50000
1#
13
#100000
0#
03
#150000
1#
13
#200000
0#
03
#250000
1#
13
#300000
0#
03
#350000
1#
13
#400000
0#
03
#450000
1#
13
1$
14
#500000
0#
03
#550000
1#
13
b11 S
0W
#600000
0#
03
#650000
1#
13
b10 S
1W
0V
#700000
0#
03
#750000
1#
13
b1 S
0W
#800000
0#
03
#850000
1#
13
b0 S
1W
1V
1U
1T
#900000
0#
03
#950000
1#
13
b100 S
1R
0U
0T
1I
1K
#1000000
0#
03
#1050000
1#
13
b11 S
1J
0K
0W
#1100000
0#
03
#1150000
1#
13
b10 S
1W
0V
#1200000
0#
03
#1250000
1#
13
b1 S
0W
#1300000
0#
03
#1350000
1#
13
b0 S
1W
1V
1U
1T
#1400000
0#
03
#1450000
1#
13
b100 S
0R
0U
0T
0I
#1500000
0#
03
#1550000
1#
13
b11 S
0J
0W
#1600000
0#
03
#1650000
1#
13
b10 S
1W
0V
#1700000
0#
03
#1750000
1#
13
b1 S
0W
#1800000
0#
03
#1850000
1#
13
b0 S
1W
1V
1U
1T
#1900000
0#
03
#1950000
1#
13
b100 S
1R
0U
0T
1I
1K
#2000000
0#
03
#2050000
1#
13
b11 S
1J
0K
0W
#2100000
0#
03
#2150000
1#
13
b10 S
1W
0V
#2200000
0#
03
#2250000
1#
13
b1 S
0W
#2300000
0#
03
#2350000
1#
13
b0 S
1W
1V
1U
1T
#2400000
0#
03
#2450000
1#
13
b1010010101011010 *
b1010010101011010 +
b110100101010110100 ,
b100 S
0R
0U
0T
0I
#2500000
0#
03
#2550000
1#
13
b11 S
0J
b1010010101011010 &
0%
1D
1B
1A
1?
1=
1;
18
16
0W
05
#2600000
0#
03
#2650000
1#
13
b10 S
1W
0V
#2700000
0#
03
#2750000
1#
13
b1 S
0W
#2800000
0#
03
#2850000
1#
13
b0 S
1W
1V
1U
1T
#2900000
0#
03
#2950000
1#
13
b100 S
1R
0U
0T
1I
1K
#3000000
0#
03
#3050000
1#
13
b11 S
1J
b1010010101011010 M
1F
0G
1H
b1 L
0K
0W
1'
0(
1)
#3051000
b0 -
#3100000
0#
03
#3150000
1#
13
b10 S
0F
1%
1W
0V
0'
15
#3200000
0#
03
#3250000
1#
13
b1 S
0W
#3300000
0#
03
#3350000
1#
13
b0 S
1W
1V
1U
1T
#3400000
0#
03
#3450000
1#
13
b100 S
0R
0U
0T
0I
#3500000
0#
03
#3550000
1#
13
b11 S
0J
0W
#3600000
0#
03
#3650000
1#
13
b10 S
1W
0V
#3700000
0#
03
#3750000
1#
13
b1 S
0W
#3800000
0#
03
#3850000
1#
13
b0 S
1W
1V
1U
1T
#3900000
0#
03
#3950000
1#
13
b100 S
1R
0U
0T
1I
1K
#4000000
0#
03
#4050000
1#
13
b11 S
1J
b101001010101101 M
b1 N
b10 L
0K
0W
#4051000
b1 -
#4100000
0#
03
#4150000
1#
13
b10 S
1W
0V
#4200000
0#
03
#4250000
1#
13
b1 S
0W
#4300000
0#
03
#4350000
1#
13
b0 S
1W
1V
1U
1T
#4400000
0#
03
#4450000
1#
13
b100 S
0R
0U
0T
0I
#4500000
0#
03
#4550000
1#
13
b11 S
0J
0W
#4600000
0#
03
#4650000
1#
13
b10 S
1W
0V
#4700000
0#
03
#4750000
1#
13
b1 S
0W
#4800000
0#
03
#4850000
1#
13
b0 S
1W
1V
1U
1T
#4900000
0#
03
#4950000
1#
13
b100 S
1R
0U
0T
1I
1K
#5000000
0#
03
#5050000
1#
13
b11 S
1J
1G
b10100101010110 M
b10 N
0K
0W
1(
#5051000
b10 -
#5100000
0#
03
#5150000
1#
13
b10 S
1W
0V
#5200000
0#
03
#5250000
1#
13
b1 S
0W
#5300000
0#
03
#5350000
1#
13
b0 S
1W
1V
1U
1T
#5400000
0#
03
#5450000
1#
13
b100 S
0R
0U
0T
0I
#5500000
0#
03
#5550000
1#
13
b11 S
0J
0W
#5600000
0#
03
#5650000
1#
13
b10 S
1W
0V
#5700000
0#
03
#5750000
1#
13
b1 S
0W
#5800000
0#
03
#5850000
1#
13
b0 S
1W
1V
1U
1T
#5900000
0#
03
#5950000
1#
13
b100 S
1R
0U
0T
1I
1K
#6000000
0#
03
#6050000
1#
13
b11 S
1J
0G
b1010010101011 M
b11 N
0K
0W
0(
#6051000
b11 -
#6100000
0#
03
#6150000
1#
13
b10 S
1W
0V
#6200000
0#
03
#6250000
1#
13
b1 S
0W
#6300000
0#
03
#6350000
1#
13
b0 S
1W
1V
1U
1T
#6400000
0#
03
#6450000
1#
13
b100 S
0R
0U
0T
0I
#6500000
0#
03
#6550000
1#
13
b11 S
0J
0W
#6600000
0#
03
#6650000
1#
13
b10 S
1W
0V
#6700000
0#
03
#6750000
1#
13
b1 S
0W
#6800000
0#
03
#6850000
1#
13
b0 S
1W
1V
1U
1T
#6900000
0#
03
#6950000
1#
13
b100 S
1R
0U
0T
1I
1K
#7000000
0#
03
#7050000
1#
13
b11 S
1J
1G
b101001010101 M
b100 N
0K
0W
1(
#7051000
b100 -
#7100000
0#
03
#7150000
1#
13
b10 S
1W
0V
#7200000
0#
03
#7250000
1#
13
b1 S
0W
#7300000
0#
03
#7350000
1#
13
b0 S
1W
1V
1U
1T
#7400000
0#
03
#7450000
1#
13
b100 S
0R
0U
0T
0I
#7500000
0#
03
#7550000
1#
13
b11 S
0J
0W
#7600000
0#
03
#7650000
1#
13
b10 S
1W
0V
#7700000
0#
03
#7750000
1#
13
b1 S
0W
#7800000
0#
03
#7850000
1#
13
b0 S
1W
1V
1U
1T
#7900000
0#
03
#7950000
1#
13
b100 S
1R
0U
0T
1I
1K
#8000000
0#
03
#8050000
1#
13
b11 S
1J
b10100101010 M
b101 N
0K
0W
#8051000
b101 -
#8100000
0#
03
#8150000
1#
13
b10 S
1W
0V
#8200000
0#
03
#8250000
1#
13
b1 S
0W
#8300000
0#
03
#8350000
1#
13
b0 S
1W
1V
1U
1T
#8400000
0#
03
#8450000
1#
13
b100 S
0R
0U
0T
0I
#8500000
0#
03
#8550000
1#
13
b11 S
0J
0W
#8600000
0#
03
#8650000
1#
13
b10 S
1W
0V
#8700000
0#
03
#8750000
1#
13
b1 S
0W
#8800000
0#
03
#8850000
1#
13
b0 S
1W
1V
1U
1T
#8900000
0#
03
#8950000
1#
13
b100 S
1R
0U
0T
1I
1K
#9000000
0#
03
#9050000
1#
13
b11 S
1J
0G
b1010010101 M
b110 N
0K
0W
0(
#9051000
b110 -
#9100000
0#
03
#9150000
1#
13
b10 S
1W
0V
#9200000
0#
03
#9250000
1#
13
b1 S
0W
#9300000
0#
03
#9350000
1#
13
b0 S
1W
1V
1U
1T
#9400000
0#
03
#9450000
1#
13
b100 S
0R
0U
0T
0I
#9500000
0#
03
#9550000
1#
13
b11 S
0J
0W
#9600000
0#
03
#9650000
1#
13
b10 S
1W
0V
#9700000
0#
03
#9750000
1#
13
b1 S
0W
#9800000
0#
03
#9850000
1#
13
b0 S
1W
1V
1U
1T
#9900000
0#
03
#9950000
1#
13
b100 S
1R
0U
0T
1I
1K
#10000000
0#
03
#10050000
1#
13
b11 S
1J
1G
b101001010 M
b111 N
0K
0W
1(
#10051000
b111 -
#10100000
0#
03
#10150000
1#
13
b10 S
1W
0V
#10200000
0#
03
#10250000
1#
13
b1 S
0W
#10300000
0#
03
#10350000
1#
13
b0 S
1W
1V
1U
1T
#10400000
0#
03
#10450000
1#
13
b100 S
0R
0U
0T
0I
#10500000
0#
03
#10550000
1#
13
b11 S
0J
0W
#10600000
0#
03
#10650000
1#
13
b10 S
1W
0V
#10700000
0#
03
#10750000
1#
13
b1 S
0W
#10800000
0#
03
#10850000
1#
13
b0 S
1W
1V
1U
1T
#10900000
0#
03
#10950000
1#
13
b100 S
1R
0U
0T
1I
1K
#11000000
0#
03
#11050000
1#
13
b11 S
1J
0G
b10100101 M
b1000 N
0K
0W
0(
#11051000
b1000 -
#11100000
0#
03
#11150000
1#
13
b10 S
1W
0V
#11200000
0#
03
#11250000
1#
13
b1 S
0W
#11300000
0#
03
#11350000
1#
13
b0 S
1W
1V
1U
1T
#11400000
0#
03
#11450000
1#
13
b100 S
0R
0U
0T
0I
#11500000
0#
03
#11550000
1#
13
b11 S
0J
0W
#11600000
0#
03
#11650000
1#
13
b10 S
1W
0V
#11700000
0#
03
#11750000
1#
13
b1 S
0W
#11800000
0#
03
#11850000
1#
13
b0 S
1W
1V
1U
1T
#11900000
0#
03
#11950000
1#
13
b100 S
1R
0U
0T
1I
1K
#12000000
0#
03
#12050000
1#
13
b11 S
1J
1G
b1010010 M
b1001 N
0K
0W
1(
#12051000
b1001 -
#12100000
0#
03
#12150000
1#
13
b10 S
1W
0V
#12200000
0#
03
#12250000
1#
13
b1 S
0W
#12300000
0#
03
#12350000
1#
13
b0 S
1W
1V
1U
1T
#12400000
0#
03
#12450000
1#
13
b100 S
0R
0U
0T
0I
#12500000
0#
03
#12550000
1#
13
b11 S
0J
0W
#12600000
0#
03
#12650000
1#
13
b10 S
1W
0V
#12700000
0#
03
#12750000
1#
13
b1 S
0W
#12800000
0#
03
#12850000
1#
13
b0 S
1W
1V
1U
1T
#12900000
0#
03
#12950000
1#
13
b100 S
1R
0U
0T
1I
1K
#13000000
0#
03
#13050000
1#
13
b11 S
1J
0G
b101001 M
b1010 N
0K
0W
0(
#13051000
b1010 -
#13100000
0#
03
#13150000
1#
13
b10 S
1W
0V
#13200000
0#
03
#13250000
1#
13
b1 S
0W
#13300000
0#
03
#13350000
1#
13
b0 S
1W
1V
1U
1T
#13400000
0#
03
#13450000
1#
13
b100 S
0R
0U
0T
0I
#13500000
0#
03
#13550000
1#
13
b11 S
0J
0W
#13600000
0#
03
#13650000
1#
13
b10 S
1W
0V
#13700000
0#
03
#13750000
1#
13
b1 S
0W
#13800000
0#
03
#13850000
1#
13
b0 S
1W
1V
1U
1T
#13900000
0#
03
#13950000
1#
13
b100 S
1R
0U
0T
1I
1K
#14000000
0#
03
#14050000
1#
13
b11 S
1J
1G
b10100 M
b1011 N
0K
0W
1(
#14051000
b1011 -
#14100000
0#
03
#14150000
1#
13
b10 S
1W
0V
#14200000
0#
03
#14250000
1#
13
b1 S
0W
#14300000
0#
03
#14350000
1#
13
b0 S
1W
1V
1U
1T
#14400000
0#
03
#14450000
1#
13
b100 S
0R
0U
0T
0I
#14500000
0#
03
#14550000
1#
13
b11 S
0J
0W
#14600000
0#
03
#14650000
1#
13
b10 S
1W
0V
#14700000
0#
03
#14750000
1#
13
b1 S
0W
#14800000
0#
03
#14850000
1#
13
b0 S
1W
1V
1U
1T
#14900000
0#
03
#14950000
1#
13
b100 S
1R
0U
0T
1I
1K
#15000000
0#
03
#15050000
1#
13
b11 S
1J
0G
b1010 M
b1100 N
0K
0W
0(
#15051000
b1100 -
#15100000
0#
03
#15150000
1#
13
b10 S
1W
0V
#15200000
0#
03
#15250000
1#
13
b1 S
0W
#15300000
0#
03
#15350000
1#
13
b0 S
1W
1V
1U
1T
#15400000
0#
03
#15450000
1#
13
b100 S
0R
0U
0T
0I
#15500000
0#
03
#15550000
1#
13
b11 S
0J
0W
#15600000
0#
03
#15650000
1#
13
b10 S
1W
0V
#15700000
0#
03
#15750000
1#
13
b1 S
0W
#15800000
0#
03
#15850000
1#
13
b0 S
1W
1V
1U
1T
#15900000
0#
03
#15950000
1#
13
b100 S
1R
0U
0T
1I
1K
#16000000
0#
03
#16050000
1#
13
b11 S
1J
b101 M
b1101 N
0K
0W
#16051000
b1101 -
#16100000
0#
03
#16150000
1#
13
b10 S
1W
0V
#16200000
0#
03
#16250000
1#
13
b1 S
0W
#16300000
0#
03
#16350000
1#
13
b0 S
1W
1V
1U
1T
#16400000
0#
03
#16450000
1#
13
b100 S
0R
0U
0T
0I
#16500000
0#
03
#16550000
1#
13
b11 S
0J
0W
#16600000
0#
03
#16650000
1#
13
b10 S
1W
0V
#16700000
0#
03
#16750000
1#
13
b1 S
0W
#16800000
0#
03
#16850000
1#
13
b0 S
1W
1V
1U
1T
#16900000
0#
03
#16950000
1#
13
b100 S
1R
0U
0T
1I
1K
#17000000
0#
03
#17050000
1#
13
b11 S
1J
1G
b10 M
b1110 N
0K
0W
1(
#17051000
b1110 -
#17100000
0#
03
#17150000
1#
13
b10 S
1W
0V
#17200000
0#
03
#17250000
1#
13
b1 S
0W
#17300000
0#
03
#17350000
1#
13
b0 S
1W
1V
1U
1T
#17400000
0#
03
#17450000
1#
13
b100 S
0R
0U
0T
0I
#17500000
0#
03
#17550000
1#
13
b11 S
0J
0W
#17600000
0#
03
#17650000
1#
13
b10 S
1W
0V
#17700000
0#
03
#17750000
1#
13
b1 S
0W
#17800000
0#
03
#17850000
1#
13
b0 S
1W
1V
1U
1T
#17900000
0#
03
#17950000
1#
13
b100 S
1R
0U
0T
1I
1K
#18000000
0#
03
#18050000
1#
13
b11 S
1J
0G
b1 M
b1111 N
0K
0W
0(
#18051000
b1111 -
#18100000
0#
03
#18150000
1#
13
b10 S
1W
0V
#18200000
0#
03
#18250000
1#
13
b1 S
0W
#18300000
0#
03
#18350000
1#
13
b0 S
1W
1V
1U
1T
#18400000
0#
03
#18450000
1#
13
b100 S
0R
0U
0T
0I
#18500000
0#
03
#18550000
1#
13
b11 S
0J
0W
#18600000
0#
03
#18650000
1#
13
b10 S
1W
0V
#18700000
0#
03
#18750000
1#
13
b1 S
0W
#18800000
0#
03
#18850000
1#
13
b0 S
1W
1V
1U
1T
#18900000
0#
03
#18950000
1#
13
b100 S
1R
0U
0T
1I
1K
#19000000
0#
03
#19050000
1#
13
b11 S
1J
1G
b0 M
b100 L
b10000 N
0K
0W
1(
#19051000
b10000 -
#19100000
0#
03
#19150000
1#
13
b10 S
1W
0V
#19200000
0#
03
#19250000
1#
13
b1 S
0W
#19300000
0#
03
#19350000
1#
13
b0 S
1W
1V
1U
1T
#19400000
0#
03
#19450000
1#
13
b100 S
0R
0U
0T
0I
#19500000
0#
03
#19550000
1#
13
b11 S
0J
0W
#19600000
0#
03
#19650000
1#
13
b10 S
1W
0V
#19700000
0#
03
#19750000
1#
13
b1 S
0W
#19800000
0#
03
#19850000
1#
13
b0 S
1W
1V
1U
1T
#19900000
0#
03
#19950000
1#
13
b100 S
1R
0U
0T
1I
1K
#20000000
0#
03
#20050000
1#
13
b11 S
1J
1O
0K
0W
#20051000
b10001 -
#20100000
0#
03
#20150000
1#
13
b10 S
1W
0V
#20200000
0#
03
#20250000
1#
13
b1 S
0W
#20300000
0#
03
#20350000
1#
13
b0 S
1W
1V
1U
1T
#20400000
0#
03
#20450000
1#
13
b100 S
0R
0U
0T
0I
#20500000
0#
03
#20550000
1#
13
b11 S
0J
0W
#20600000
0#
03
#20650000
1#
13
b10 S
1W
0V
#20700000
0#
03
#20750000
1#
13
b1 S
0W
#20800000
0#
03
#20850000
1#
13
b0 S
1W
1V
1U
1T
#20900000
0#
03
#20950000
1#
13
b100 S
1R
0U
0T
1I
1K
#21000000
0#
03
