FPGA_FIFO/rtl/Async_FIFO.v
//============================================================
// Module Name : Async_FIFO
// Description : Asynchronous Register-Based FIFO with Gray Code CDC
//
// Function:
//   - Safely transfers data between a high-speed write clock domain
//     and a slower read clock domain using 2-flip-flop synchronizers.
//   - Uses Gray code to prevent metastability during pointer transfer.
//   - Full and Empty flags are generated in their respective domains.
//
// Example:
//   If AddrWidth = 4
//   FIFO Depth = 16 entries
//
// Notes:
//   - Pointers are maintained with an extra MSB (N+1 bits) to
//     distinguish between wrap-around (Full) and catch-up (Empty).
//   - Register-based memory is used instead of Block RAM to allow
//     low latency and distributed logic implementation.
//============================================================

module Async_FIFO
#(
    parameter AddrWidth = 4, // Pointer width (defines FIFO depth as 2^AddrWidth)
    parameter DataWidth = 16 // Width of the data bus
)
(
    input  wire                 iWClk,   // Write domain clock
    input  wire                 iWRstN,  // Write domain asynchronous active-low reset
    input  wire                 iRClk,   // Read domain clock
    input  wire                 iRRstN,  // Read domain asynchronous active-low reset
    input  wire [DataWidth-1:0] iData,   // Data input to be written
    input  wire                 iWInc,   // Write increment (enable) signal
    input  wire                 iRInc,   // Read increment (enable) signal
    output wire [DataWidth-1:0] oData,   // Data output being read
    output reg                  oFull,   // FIFO full flag (sync'd to iWClk)
    output reg                  oEmpty   // FIFO empty flag (sync'd to iRClk)
);

    //--------------------------------------------------------
    // Memory Array Initialization
    //
    // Depth is calculated from the parameter AddrWidth.
    // A register array is used for the memory block.
    //--------------------------------------------------------
    localparam Depth = 1 << AddrWidth;
    reg [DataWidth-1:0] Mem [0:Depth-1];

    //--------------------------------------------------------
    // Pointers Declaration
    //
    // Pointers are N+1 bits wide [AddrWidth:0] to handle the 
    // wrap-around condition, allowing distinction between 
    // Full and Empty states.
    //--------------------------------------------------------
    reg  [AddrWidth:0] wPtrBin, rPtrBin;   // Binary pointers for memory addressing
    reg  [AddrWidth:0] wPtrGray, rPtrGray; // Gray code pointers for CDC transfer
    
    wire [AddrWidth:0] wPtrGrayNext, rPtrGrayNext;
    wire [AddrWidth:0] wPtrBinNext, rPtrBinNext;

    // Synchronizer registers (2-FF synchronization chain)
    reg [AddrWidth:0] wQ1RPtr, wQ2RPtr; // Read pointer synchronized into Write domain
    reg [AddrWidth:0] rQ1WPtr, rQ2WPtr; // Write pointer synchronized into Read domain

    //--------------------------------------------------------
    // Memory Write & Read Logic
    //
    // Write operation: Synchronous to iWClk. Only writes if 
    // requested and FIFO is not full.
    // Read operation: Combinatorial assignment directly from 
    // the register array.
    //--------------------------------------------------------
    always @(posedge iWClk) begin
        if (iWInc && !oFull) begin
            Mem[wPtrBin[AddrWidth-1:0]] <= iData;
        end
    end

    assign oData = Mem[rPtrBin[AddrWidth-1:0]];

    //--------------------------------------------------------
    // Write Domain: Pointer Management & Gray Code
    //
    // Calculates the next binary pointer and converts it to 
    // Gray code (G = B XOR (B >> 1)).
    //--------------------------------------------------------
    always @(posedge iWClk or negedge iWRstN) begin
        if (!iWRstN) begin
            wPtrBin  <= 0;
            wPtrGray <= 0;
        end else begin
            wPtrBin  <= wPtrBinNext;
            wPtrGray <= wPtrGrayNext;
        end
    end

    assign wPtrBinNext  = wPtrBin + (iWInc & ~oFull);
    assign wPtrGrayNext = wPtrBinNext ^ (wPtrBinNext >> 1);

    //--------------------------------------------------------
    // Read Domain: Pointer Management & Gray Code
    //
    // Calculates the next binary read pointer and converts it 
    // to Gray code.
    //--------------------------------------------------------
    always @(posedge iRClk or negedge iRRstN) begin
        if (!iRRstN) begin
            rPtrBin  <= 0;
            rPtrGray <= 0;
        end else begin
            rPtrBin  <= rPtrBinNext;
            rPtrGray <= rPtrGrayNext;
        end
    end

    assign rPtrBinNext  = rPtrBin + (iRInc & ~oEmpty);
    assign rPtrGrayNext = rPtrBinNext ^ (rPtrBinNext >> 1);

    //--------------------------------------------------------
    // Clock Domain Crossing (CDC) - 2-FF Synchronizers
    //
    // Safely transfers the Gray code pointers across the clock
    // domains using two stages of flip-flops to mitigate 
    // metastability.
    //--------------------------------------------------------
    always @(posedge iWClk or negedge iWRstN) begin
        if (!iWRstN) begin
            wQ1RPtr <= 0;
            wQ2RPtr <= 0;
        end else begin
            wQ1RPtr <= rPtrGray; 
            wQ2RPtr <= wQ1RPtr;  
        end
    end

    always @(posedge iRClk or negedge iRRstN) begin
        if (!iRRstN) begin
            rQ1WPtr <= 0;
            rQ2WPtr <= 0;
        end else begin
            rQ1WPtr <= wPtrGray; 
            rQ2WPtr <= rQ1WPtr;  
        end
    end

    //--------------------------------------------------------
    // Full & Empty Condition Logic
    //
    // Empty condition is evaluated in the Read domain when 
    // the read pointer catches up to the synchronized write pointer.
    //
    // Full condition is evaluated in the Write domain when 
    // the synchronized read pointer's 2 MSBs are inverted 
    // compared to the write pointer.
    //--------------------------------------------------------
    wire rEmptyVal;
    assign rEmptyVal = (rPtrGrayNext == rQ2WPtr);
    
    always @(posedge iRClk or negedge iRRstN) begin
        if (!iRRstN) oEmpty <= 1'b1;
        else         oEmpty <= rEmptyVal;
    end

    wire wFullVal;
    assign wFullVal = (wPtrGrayNext == {~wQ2RPtr[AddrWidth:AddrWidth-1], wQ2RPtr[AddrWidth-2:0]});
    
    always @(posedge iWClk or negedge iWRstN) begin
        if (!iWRstN) oFull <= 1'b0;
        else         oFull <= wFullVal;
    end

endmodule

FPGA_FIFO/Async_FIFO_TB.v
`timescale 1ns / 1ps

//============================================================
// Module Name : Async_FIFO_TB
// Description : Testbench for Asynchronous Register-Based FIFO
//
// Function:
//   - Simulates high-speed write and slow-speed read domains.
//   - Verifies Full and Empty flag generation across CDCs.
//   - Dumps waveforms to a VCD file for visualization.
//============================================================

module Async_FIFO_TB;

    //--------------------------------------------------------
    // Parameters & Signals
    //--------------------------------------------------------
    parameter DataWidth = 16;
    parameter AddrWidth = 4; // Depth = 16

    // Write Domain Signals (Registers for driving inputs)
    reg                  iWClk;
    reg                  iWRstN;
    reg                  iWInc;
    reg  [DataWidth-1:0] iData;
    wire                 oFull;

    // Read Domain Signals (Registers for driving inputs, wires for outputs)
    reg                  iRClk;
    reg                  iRRstN;
    reg                  iRInc;
    wire [DataWidth-1:0] oData;
    wire                 oEmpty;

    //--------------------------------------------------------
    // Unit Under Test (UUT) Instantiation
    //--------------------------------------------------------
    Async_FIFO #(
        .AddrWidth(AddrWidth),
        .DataWidth(DataWidth)
    ) uut (
        .iWClk  (iWClk),
        .iWRstN (iWRstN),
        .iRClk  (iRClk),
        .iRRstN (iRRstN),
        .iData  (iData),
        .iWInc  (iWInc),
        .iRInc  (iRInc),
        .oData  (oData),
        .oFull  (oFull),
        .oEmpty (oEmpty)
    );

    //--------------------------------------------------------
    // Clock Generation
    //
    // Write clock: 10ns period (Fast Clock - e.g., 100MHz)
    // Read clock : 25ns period (Slow Clock - e.g., 40MHz)
    //--------------------------------------------------------
    always #5 iWClk = ~iWClk;
    always #12.5 iRClk = ~iRClk;

    //--------------------------------------------------------
    // Test Sequence
    //--------------------------------------------------------
    integer Idx;

    initial begin
        // Tell Icarus Verilog to dump waveforms for viewing
        $dumpfile("fifo_waves.vcd");
        $dumpvars(0, Async_FIFO_TB);

        // Initialize all inputs
        iWClk  = 0;
        iRClk  = 0;
        iWRstN = 0;
        iRRstN = 0;
        iWInc  = 0;
        iRInc  = 0;
        iData  = 0;

        // Apply Resets
        #20;
        iWRstN = 1;
        iRRstN = 1;
        #20;

        $display("----------------------------------------");
        $display("Test 1: Write until FULL");
        $display("----------------------------------------");
        
        // Wait for a negative clock edge to assign values safely
        @(negedge iWClk);
        
        // Loop 18 times (FIFO depth is 16, so it should stop writing when full)
        for (Idx = 0; Idx < 18; Idx = Idx + 1) begin
            if (!oFull) begin
                iWInc = 1;
                iData = Idx * 10; // Write dummy data (0, 10, 20, 30...)
                $display("[Write Domain] Wrote data: %0d", iData);
            end else begin
                iWInc = 0;
                $display("[Write Domain] FIFO is FULL. Write blocked.");
            end
            @(negedge iWClk);
        end
        iWInc = 0; // Stop writing
        
        #100; // Wait a bit to let CDC synchronizers settle

        $display("----------------------------------------");
        $display("Test 2: Read until EMPTY");
        $display("----------------------------------------");
        
        @(negedge iRClk);
        for (Idx = 0; Idx < 18; Idx = Idx + 1) begin
            if (!oEmpty) begin
                iRInc = 1;
                $display("[Read Domain] Read data: %0d", oData);
            end else begin
                iRInc = 0;
                $display("[Read Domain] FIFO is EMPTY. Read blocked.");
            end
            @(negedge iRClk);
        end
        iRInc = 0; // Stop reading

        #50;
        $display("----------------------------------------");
        $display("Testbench Completed Successfully!");
        $display("----------------------------------------");
        
        // End the simulation
        $finish;
    end

endmodule

FPGA_FIFO/fifo_waves.vcd
$date
	Sun Jun 21 22:21:52 2026
$end
$version
	Icarus Verilog
$end
$timescale
	1ps
$end
$scope module Async_FIFO_TB $end
$var wire 1 ! oFull $end
$var wire 1 " oEmpty $end
$var wire 16 # oData [15:0] $end
$var parameter 32 $ AddrWidth $end
$var parameter 32 % DataWidth $end
$var reg 16 & iData [15:0] $end
$var reg 1 ' iRClk $end
$var reg 1 ( iRInc $end
$var reg 1 ) iRRstN $end
$var reg 1 * iWClk $end
$var reg 1 + iWInc $end
$var reg 1 , iWRstN $end
$var integer 32 - Idx [31:0] $end
$scope module uut $end
$var wire 16 . iData [15:0] $end
$var wire 1 ' iRClk $end
$var wire 1 ( iRInc $end
$var wire 1 ) iRRstN $end
$var wire 1 * iWClk $end
$var wire 1 + iWInc $end
$var wire 1 , iWRstN $end
$var wire 16 / oData [15:0] $end
$var wire 5 0 rPtrGrayNext [4:0] $end
$var wire 5 1 wPtrGrayNext [4:0] $end
$var wire 5 2 wPtrBinNext [4:0] $end
$var wire 1 3 wFullVal $end
$var wire 5 4 rPtrBinNext [4:0] $end
$var wire 1 5 rEmptyVal $end
$var parameter 32 6 AddrWidth $end
$var parameter 32 7 DataWidth $end
$var parameter 36 8 Depth $end
$var reg 1 " oEmpty $end
$var reg 1 ! oFull $end
$var reg 5 9 rPtrBin [4:0] $end
$var reg 5 : rPtrGray [4:0] $end
$var reg 5 ; rQ1WPtr [4:0] $end
$var reg 5 < rQ2WPtr [4:0] $end
$var reg 5 = wPtrBin [4:0] $end
$var reg 5 > wPtrGray [4:0] $end
$var reg 5 ? wQ1RPtr [4:0] $end
$var reg 5 @ wQ2RPtr [4:0] $end
$upscope $end
$upscope $end
$enddefinitions $end
$comment Show the parameter values. $end
$dumpall
b10000 8
b10000 7
b100 6
b10000 %
b100 $
$end
#0
$dumpvars
b0 @
b0 ?
b0 >
b0 =
b0 <
b0 ;
b0 :
b0 9
15
b0 4
03
b0 2
b0 1
b0 0
bx /
b0 .
bx -
0,
0+
0*
0)
0(
0'
b0 &
bx #
1"
0!
$end
#5000
1*
#10000
0*
#12500
1'
#15000
1*
#20000
0*
1)
1,
#25000
1*
0'
#30000
0*
#35000
1*
#37500
1'
#40000
b1 1
b1 2
1+
b0 -
0*
#45000
b11 1
b1 >
b10 2
b1 =
b0 #
b0 /
1*
#50000
b1010 &
b1010 .
b1 -
0*
0'
#55000
b10 1
b11 >
b11 2
b10 =
1*
#60000
b10100 &
b10100 .
b10 -
0*
#62500
b11 ;
1'
#65000
b110 1
b10 >
b100 2
b11 =
1*
#70000
b11110 &
b11110 .
b11 -
0*
#75000
b111 1
b110 >
b101 2
b100 =
1*
0'
#80000
b101000 &
b101000 .
b100 -
0*
#85000
b101 1
b111 >
b110 2
b101 =
1*
#87500
05
b11 <
b111 ;
1'
#90000
b110010 &
b110010 .
b101 -
0*
#95000
b100 1
b101 >
b111 2
b110 =
1*
#100000
b111100 &
b111100 .
b110 -
0*
0'
#105000
b1100 1
b100 >
b1000 2
b111 =
1*
#110000
b1000110 &
b1000110 .
b111 -
0*
#112500
0"
b111 <
b100 ;
1'
#115000
b1101 1
b1100 >
b1001 2
b1000 =
1*
#120000
b1010000 &
b1010000 .
b1000 -
0*
#125000
b1111 1
b1101 >
b1010 2
b1001 =
1*
0'
#130000
b1011010 &
b1011010 .
b1001 -
0*
#135000
b1110 1
b1111 >
b1011 2
b1010 =
1*
#137500
b100 <
b1111 ;
1'
#140000
b1100100 &
b1100100 .
b1010 -
0*
#145000
b1010 1
b1110 >
b1100 2
b1011 =
1*
#150000
b1101110 &
b1101110 .
b1011 -
0*
0'
#155000
b1011 1
b1010 >
b1101 2
b1100 =
1*
#160000
b1111000 &
b1111000 .
b1100 -
0*
#162500
b1111 <
b1010 ;
1'
#165000
b1001 1
b1011 >
b1110 2
b1101 =
1*
#170000
b10000010 &
b10000010 .
b1101 -
0*
#175000
b1000 1
b1001 >
b1111 2
b1110 =
1*
0'
#180000
b10001100 &
b10001100 .
b1110 -
0*
#185000
13
b11000 1
b1000 >
b10000 2
b1111 =
1*
#187500
b1010 <
b1000 ;
1'
#190000
b10010110 &
b10010110 .
b1111 -
0*
#195000
13
b11000 1
b11000 >
b10000 2
b10000 =
1!
1*
#200000
0+
b10000 -
0*
0'
#205000
1*
#210000
b10001 -
0*
#212500
b1000 <
b11000 ;
1'
#215000
1*
#220000
b10010 -
0*
#225000
1*
0'
#230000
0*
#235000
1*
#237500
b11000 <
1'
#240000
0*
#245000
1*
#250000
0*
0'
#255000
1*
#260000
0*
#262500
1'
#265000
1*
#270000
0*
#275000
1*
0'
#280000
0*
#285000
1*
#287500
1'
#290000
0*
#295000
1*
#300000
0*
0'
#305000
1*
#310000
0*
#312500
1'
#315000
1*
#320000
0*
#325000
b1 0
b1 4
1(
b0 -
1*
0'
#330000
0*
#335000
1*
#337500
b1010 #
b1010 /
b11 0
b1 :
b10 4
b1 9
1'
#340000
0*
#345000
b1 ?
1*
#350000
b1 -
0*
0'
#355000
03
b1 @
1*
#360000
0*
#362500
b10100 #
b10100 /
b10 0
b11 :
b11 4
b10 9
1'
#365000
0!
b11 ?
1*
#370000
0*
#375000
b11 @
b10 -
1*
0'
#380000
0*
#385000
1*
#387500
b11110 #
b11110 /
b110 0
b10 :
b100 4
b11 9
1'
#390000
0*
#395000
b10 ?
1*
#400000
b11 -
0*
0'
#405000
b10 @
1*
#410000
0*
#412500
b101000 #
b101000 /
b111 0
b110 :
b101 4
b100 9
1'
#415000
b110 ?
1*
#420000
0*
#425000
b110 @
b100 -
1*
0'
#430000
0*
#435000
1*
#437500
b110010 #
b110010 /
b101 0
b111 :
b110 4
b101 9
1'
#440000
0*
#445000
b111 ?
1*
#450000
b101 -
0*
0'
#455000
b111 @
1*
#460000
0*
#462500
b111100 #
b111100 /
b100 0
b101 :
b111 4
b110 9
1'
#465000
b101 ?
1*
#470000
0*
#475000
b101 @
b110 -
1*
0'
#480000
0*
#485000
1*
#487500
b1000110 #
b1000110 /
b1100 0
b100 :
b1000 4
b111 9
1'
#490000
0*
#495000
b100 ?
1*
#500000
b111 -
0*
0'
#505000
b100 @
1*
#510000
0*
#512500
b1010000 #
b1010000 /
b1101 0
b1100 :
b1001 4
b1000 9
1'
#515000
b1100 ?
1*
#520000
0*
#525000
b1100 @
b1000 -
1*
0'
#530000
0*
#535000
1*
#537500
b1011010 #
b1011010 /
b1111 0
b1101 :
b1010 4
b1001 9
1'
#540000
0*
#545000
b1101 ?
1*
#550000
b1001 -
0*
0'
#555000
b1101 @
1*
#560000
0*
#562500
b1100100 #
b1100100 /
b1110 0
b1111 :
b1011 4
b1010 9
1'
#565000
b1111 ?
1*
#570000
0*
#575000
b1111 @
b1010 -
1*
0'
#580000
0*
#585000
1*
#587500
b1101110 #
b1101110 /
b1010 0
b1110 :
b1100 4
b1011 9
1'
#590000
0*
#595000
b1110 ?
1*
#600000
b1011 -
0*
0'
#605000
b1110 @
1*
#610000
0*
#612500
b1111000 #
b1111000 /
b1011 0
b1010 :
b1101 4
b1100 9
1'
#615000
b1010 ?
1*
#620000
0*
#625000
b1010 @
b1100 -
1*
0'
#630000
0*
#635000
1*
#637500
b10000010 #
b10000010 /
b1001 0
b1011 :
b1110 4
b1101 9
1'
#640000
0*
#645000
b1011 ?
1*
#650000
b1101 -
0*
0'
#655000
b1011 @
1*
#660000
0*
#662500
b10001100 #
b10001100 /
b1000 0
b1001 :
b1111 4
b1110 9
1'
#665000
b1001 ?
1*
#670000
0*
#675000
b1001 @
b1110 -
1*
0'
#680000
0*
#685000
1*
#687500
15
b10010110 #
b10010110 /
b11000 0
b1000 :
b10000 4
b1111 9
1'
#690000
0*
#695000
b1000 ?
1*
#700000
b1111 -
0*
0'
#705000
b1000 @
1*
#710000
0*
#712500
b0 #
b0 /
15
b11000 0
1"
b11000 :
b10000 4
b10000 9
1'
#715000
b11000 ?
1*
#720000
0*
#725000
b11000 @
0(
b10000 -
1*
0'
#730000
0*
#735000
1*
#737500
1'
#740000
0*
#745000
1*
#750000
b10001 -
0*
0'
#755000
1*
#760000
0*
#762500
1'
#765000
1*
#770000
0*
#775000
b10010 -
1*
0'
