FPGA_FIR_Filter/FIR_Filter.v
//============================================================
// Module Name : FIR_Filter
// Description : 4-Tap Moving Average FIR Filter
//
// Function:
//   - Implements a shift register to hold the last 4 data samples.
//   - Calculates the average of the 4 samples in a single clock cycle.
//   - Fully pipelined and synchronous.
//
// Example:
//   If iData is an 8-bit stream, the filter keeps a 32-bit history
//   window (4 x 8-bit) and outputs the moving average, preventing
//   overflow and avoiding complex multi-cycle memory accesses.
//============================================================

module FIR_Filter
#(
    parameter DataWidth = 8 // Width of the input and output data bus
)
(
    input  wire                 iClk,   // Main processing clock (Fast Clock)
    input  wire                 iRstN,  // Asynchronous active-low reset
    input  wire [DataWidth-1:0] iData,  // Streaming input data sample
    output reg  [DataWidth-1:0] oData   // Averaged output data
);

    //--------------------------------------------------------
    // Shift Register (Sliding Window)
    //
    // Holds the 4 most recent data samples in a continuous
    // streaming pipeline.
    //--------------------------------------------------------
    reg [DataWidth-1:0] rReg0;
    reg [DataWidth-1:0] rReg1;
    reg [DataWidth-1:0] rReg2;
    reg [DataWidth-1:0] rReg3;

    //--------------------------------------------------------
    // Combinatorial Math (Adder Tree)
    //
    // Sums all 4 registers in parallel. 
    // The width is extended by 2 bits (DataWidth+1 : 0) to 
    // safely hold the maximum possible sum without overflow.
    //--------------------------------------------------------
    wire [DataWidth+1:0] wSum;
    
    assign wSum = rReg0 + rReg1 + rReg2 + rReg3;

    //--------------------------------------------------------
    // Shift and Calculate Logic
    //
    // Reset:
    //   - Clears all registers and output to zero.
    //
    // Normal operation:
    //   - Shifts data down the pipeline.
    //   - Samples the divided sum (average) in the same clock edge.
    //   - Division by 4 is optimized by discarding the 2 LSBs
    //     (taking bits [DataWidth+1 : 2] from wSum).
    //--------------------------------------------------------
    always @(posedge iClk or negedge iRstN) begin
        if (!iRstN) begin
            rReg0 <= 0;
            rReg1 <= 0;
            rReg2 <= 0;
            rReg3 <= 0;
            oData <= 0;
        end
        else begin
            // Shift the data stream
            rReg0 <= iData;
            rReg1 <= rReg0;
            rReg2 <= rReg1;
            rReg3 <= rReg2;
            
            // Calculate and register the average (Sum / 4)
            oData <= wSum[DataWidth+1:2];
        end
    end

endmodule

FPGA_FIR_Filter/FIR_Filter_TB.v
`timescale 1ns / 1ps

//============================================================
// Module Name : FIR_Filter_TB
// Description : Testbench for the 4-Tap Moving Average FIR Filter
//
// Function:
//   - Verifies the sliding window shift register and averaging logic.
//   - Feeds a continuous stream of 8-bit data into the filter.
//   - Dumps waveforms to a VCD file for visualization.
//============================================================

module FIR_Filter_TB;

    //--------------------------------------------------------
    // Parameters & Signals
    //--------------------------------------------------------
    parameter DataWidth = 8;

    // Inputs to the DUT (Registers in TB)
    reg                  iClk;
    reg                  iRstN;
    reg  [DataWidth-1:0] iData;

    // Outputs from the DUT (Wires in TB)
    wire [DataWidth-1:0] oData;

    //--------------------------------------------------------
    // Unit Under Test (UUT) Instantiation
    //--------------------------------------------------------
    FIR_Filter #(
        .DataWidth(DataWidth)
    ) uut (
        .iClk  (iClk),
        .iRstN (iRstN),
        .iData (iData),
        .oData (oData)
    );

    //--------------------------------------------------------
    // Clock Generation
    //
    // 10ns period -> 100MHz fast processing clock
    //--------------------------------------------------------
    always #5 iClk = ~iClk;

    //--------------------------------------------------------
    // Test Sequence
    //--------------------------------------------------------
    integer Idx;

    initial begin
        // Setup waveform dumping for VSCode WaveTrace/GTKWave
        $dumpfile("fir_waves.vcd");
        $dumpvars(0, FIR_Filter_TB);

        // Initialize inputs
        iClk  = 0;
        iRstN = 0;
        iData = 0;

        // Apply asynchronous reset
        #20;
        iRstN = 1;
        #20;

        $display("----------------------------------------");
        $display("Starting FIR Filter Data Stream Test");
        $display("----------------------------------------");

        // Test 1: Ramp up (Sequence: 10, 20, 30, 40, 50...)
        @(negedge iClk);
        for (Idx = 1; Idx <= 8; Idx = Idx + 1) begin
            iData = Idx * 10;
            @(negedge iClk);
            $display("Time: %0t | Input Data: %3d | Output Average: %3d", $time, iData, oData);
        end

        $display("----------------------------------------");
        $display("Test 2: Constant Data (Wait for filter to stabilize)");
        $display("----------------------------------------");
        // Test 2: Feed constant data (100)
        for (Idx = 0; Idx < 5; Idx = Idx + 1) begin
            iData = 100;
            @(negedge iClk);
            $display("Time: %0t | Input Data: %3d | Output Average: %3d", $time, iData, oData);
        end

        $display("----------------------------------------");
        $display("Test 3: Flushing the filter (Zeros)");
        $display("----------------------------------------");
        // Test 3: Feed zeros to flush the shift registers
        for (Idx = 0; Idx < 5; Idx = Idx + 1) begin
            iData = 0;
            @(negedge iClk);
            $display("Time: %0t | Input Data: %3d | Output Average: %3d", $time, iData, oData);
        end

        #50;
        $display("----------------------------------------");
        $display("Testbench Completed Successfully!");
        $display("----------------------------------------");
        $finish;
    end

endmodule

FPGA_FIR_Filter/fir_waves.vcd
$date
	Sun Jun 21 22:43:34 2026
$end
$version
	Icarus Verilog
$end
$timescale
	1ps
$end
$scope module FIR_Filter_TB $end
$var wire 8 ! oData [7:0] $end
$var parameter 32 " DataWidth $end
$var reg 1 # iClk $end
$var reg 8 $ iData [7:0] $end
$var reg 1 % iRstN $end
$var integer 32 & Idx [31:0] $end
$scope module uut $end
$var wire 1 # iClk $end
$var wire 8 ' iData [7:0] $end
$var wire 1 % iRstN $end
$var wire 10 ( wSum [9:0] $end
$var parameter 32 ) DataWidth $end
$var reg 8 * oData [7:0] $end
$var reg 8 + rReg0 [7:0] $end
$var reg 8 , rReg1 [7:0] $end
$var reg 8 - rReg2 [7:0] $end
$var reg 8 . rReg3 [7:0] $end
$upscope $end
$upscope $end
$enddefinitions $end
$comment Show the parameter values. $end
$dumpall
b1000 )
b1000 "
$end
#0
$dumpvars
b0 .
b0 -
b0 ,
b0 +
b0 *
b0 (
b0 '
bx &
0%
b0 $
0#
b0 !
$end
#5000
1#
#10000
0#
#15000
1#
#20000
0#
1%
#25000
1#
#30000
0#
#35000
1#
#40000
b1010 $
b1010 '
b1 &
0#
#45000
b1010 (
b1010 +
1#
#50000
b10100 $
b10100 '
b10 &
0#
#55000
b10 !
b10 *
b1010 ,
b11110 (
b10100 +
1#
#60000
b11110 $
b11110 '
b11 &
0#
#65000
b111 !
b111 *
b1010 -
b10100 ,
b111100 (
b11110 +
1#
#70000
b101000 $
b101000 '
b100 &
0#
#75000
b1111 !
b1111 *
b1010 .
b10100 -
b11110 ,
b1100100 (
b101000 +
1#
#80000
b110010 $
b110010 '
b101 &
0#
#85000
b11001 !
b11001 *
b10100 .
b11110 -
b101000 ,
b10001100 (
b110010 +
1#
#90000
b111100 $
b111100 '
b110 &
0#
#95000
b100011 !
b100011 *
b11110 .
b101000 -
b110010 ,
b10110100 (
b111100 +
1#
#100000
b1000110 $
b1000110 '
b111 &
0#
#105000
b101101 !
b101101 *
b101000 .
b110010 -
b111100 ,
b11011100 (
b1000110 +
1#
#110000
b1010000 $
b1010000 '
b1000 &
0#
#115000
b110111 !
b110111 *
b110010 .
b111100 -
b1000110 ,
b100000100 (
b1010000 +
1#
#120000
b1100100 $
b1100100 '
b0 &
0#
#125000
b1000001 !
b1000001 *
b111100 .
b1000110 -
b1010000 ,
b100110110 (
b1100100 +
1#
#130000
b1 &
0#
#135000
b1001101 !
b1001101 *
b1000110 .
b1010000 -
b101011110 (
b1100100 ,
1#
#140000
b10 &
0#
#145000
b1010111 !
b1010111 *
b1010000 .
b101111100 (
b1100100 -
1#
#150000
b11 &
0#
#155000
b1011111 !
b1011111 *
b110010000 (
b1100100 .
1#
#160000
b100 &
0#
#165000
b1100100 !
b1100100 *
1#
#170000
b0 $
b0 '
b0 &
0#
#175000
b100101100 (
b0 +
1#
#180000
b1 &
0#
#185000
b1001011 !
b1001011 *
b11001000 (
b0 ,
1#
#190000
b10 &
0#
#195000
b110010 !
b110010 *
b1100100 (
b0 -
1#
#200000
b11 &
0#
#205000
b11001 !
b11001 *
b0 (
b0 .
1#
#210000
b100 &
0#
#215000
b0 !
b0 *
1#
#220000
b101 &
0#
