FPGA_FIR_Filter/FIR_Filter.v
//============================================================
// Module Name : FIR_Filter
// Description : 4-Tap Weighted FIR Filter (Coefficients: 1, 2, 3, 4)
//
// Function:
//   - Implements a shift register to hold the last 4 data samples.
//   - Updates the pipeline and calculates the weighted sum ONLY 
//     when input is valid (iValidIn).
//   - Combinatorial multiplication using shift-and-add logic:
//       oDataOut = (x[0]*1) + (x[1]*2) + (x[2]*3) + (x[3]*4)
//   - Fully pipelined: Valid output is indicated by oValidOut.
//============================================================

module FIR_Filter (
    input  wire        iClkFast,  // Fast domain clock
    input  wire        iRstN,     // Asynchronous active-low reset
    input  wire [7:0]  iDataIn,   // Streaming input data sample
    input  wire        iValidIn,  // Indicates current input is valid
    output reg  [15:0] oDataOut,  // Weighted sum output (Wide to prevent overflow)
    output reg         oValidOut  // Indicates output is ready (Connects to FIFO WE)
);

    //--------------------------------------------------------
    // Shift Register (Sliding Window)
    //--------------------------------------------------------
    reg [7:0] rX0; // Newest sample  (x[0])
    reg [7:0] rX1; // Delayed sample (x[1])
    reg [7:0] rX2; // Delayed sample (x[2])
    reg [7:0] rX3; // Oldest sample  (x[3])

    //--------------------------------------------------------
    // Combinatorial Math (Shift and Add)
    //
    // To achieve a fully pipelined design, we calculate the 
    // NEXT sum combinatorially using the incoming iDataIn 
    // as the new x[0], and the current registers as the rest.
    //--------------------------------------------------------
    wire [15:0] wX0 = iDataIn; // x[0]
    wire [15:0] wX1 = rX0;     // x[1]
    wire [15:0] wX2 = rX1;     // x[2]
    wire [15:0] wX3 = rX2;     // x[3]

    // Multiplications using bit-shifts:
    wire [15:0] wTerm0 = wX0;                        // x[0] * 1
    wire [15:0] wTerm1 = wX1 << 1;                   // x[1] * 2
    wire [15:0] wTerm2 = (wX2 << 1) + wX2;           // x[2] * 3
    wire [15:0] wTerm3 = wX3 << 2;                   // x[3] * 4

    // Combinatorial adder tree
    wire [15:0] wNextSum = wTerm0 + wTerm1 + wTerm2 + wTerm3;

    //--------------------------------------------------------
    // Pipeline Registers and Shift Logic
    //--------------------------------------------------------
    always @(posedge iClkFast or negedge iRstN) begin
        if (!iRstN) begin
            rX0 <= 8'b0;
            rX1 <= 8'b0;
            rX2 <= 8'b0;
            rX3 <= 8'b0;
            oDataOut  <= 16'b0;
            oValidOut <= 1'b0;
        end
        else begin
            // Valid output flag follows valid input with a 1-cycle pipeline delay
            oValidOut <= iValidIn;
            
            // Shift and update math ONLY when input data is valid
            if (iValidIn) begin
                rX0 <= iDataIn;
                rX1 <= rX0;
                rX2 <= rX1;
                rX3 <= rX2;
                
                // Register the calculated weighted sum
                oDataOut <= wNextSum;
            end
            // If !iValidIn, the registers (and oDataOut) safely hold their state.
        end
    end

endmodule

FPGA_FIR_Filter/FIR_Filter_TB.v
`timescale 1ns / 1ps

//============================================================
// Module Name : FIR_Filter_TB
// Description : Testbench for the 4-Tap Weighted FIR Filter
//
// Function:
//   - Verifies the sliding window and shift-add multiplication.
//   - Drives iValidIn to test pipeline stalls/holds.
//   - Dumps waveforms to a VCD file for visualization.
//============================================================

module FIR_Filter_TB;

    //--------------------------------------------------------
    // Parameters & Signals
    //--------------------------------------------------------
    // Inputs to the DUT (Registers in TB)
    reg         iClkFast;
    reg         iRstN;
    reg  [7:0]  iDataIn;
    reg         iValidIn;

    // Outputs from the DUT (Wires in TB)
    wire [15:0] oDataOut;
    wire        oValidOut;

    //--------------------------------------------------------
    // Unit Under Test (UUT) Instantiation
    //--------------------------------------------------------
    FIR_Filter uut (
        .iClkFast  (iClkFast),
        .iRstN     (iRstN),
        .iDataIn   (iDataIn),
        .iValidIn  (iValidIn),
        .oDataOut  (oDataOut),
        .oValidOut (oValidOut)
    );

    //--------------------------------------------------------
    // Clock Generation
    //
    // 10ns period -> 100MHz fast processing clock
    //--------------------------------------------------------
    always #5 iClkFast = ~iClkFast;

    //--------------------------------------------------------
    // Test Sequence
    //--------------------------------------------------------
    integer Idx;

    initial begin
        // Setup waveform dumping for VSCode WaveTrace/GTKWave
        $dumpfile("fir_waves.vcd");
        $dumpvars(0, FIR_Filter_TB);

        // Initialize inputs
        iClkFast = 0;
        iRstN    = 0;
        iDataIn  = 0;
        iValidIn = 0;

        // Apply asynchronous reset
        #20;
        iRstN = 1;
        #20;

        $display("----------------------------------------");
        $display("Starting Weighted FIR Filter Data Stream Test");
        $display("----------------------------------------");

        // Test 1: Ramp up with valid data (Sequence: 10, 20, 30, 40, 50...)
        @(negedge iClkFast);
        iValidIn = 1;
        for (Idx = 1; Idx <= 5; Idx = Idx + 1) begin
            iDataIn = Idx * 10;
            @(negedge iClkFast);
            $display("Time: %0t | Valid In: %b | Data In: %3d || Valid Out: %b | Data Out: %4d", 
                     $time, iValidIn, iDataIn, oValidOut, oDataOut);
        end

        $display("----------------------------------------");
        $display("Test 2: Pause Stream (iValidIn = 0)");
        $display("Filter should hold state and oValidOut should drop to 0");
        $display("----------------------------------------");
        iValidIn = 0;
        iDataIn  = 99; // Put garbage on the bus to ensure it's ignored
        for (Idx = 0; Idx < 3; Idx = Idx + 1) begin
            @(negedge iClkFast);
            $display("Time: %0t | Valid In: %b | Data In: %3d || Valid Out: %b | Data Out: %4d", 
                     $time, iValidIn, iDataIn, oValidOut, oDataOut);
        end

        $display("----------------------------------------");
        $display("Test 3: Resume Stream with Constant Data (10)");
        $display("Output should eventually stabilize at 10*1 + 10*2 + 10*3 + 10*4 = 100");
        $display("----------------------------------------");
        iValidIn = 1;
        for (Idx = 0; Idx < 5; Idx = Idx + 1) begin
            iDataIn = 10;
            @(negedge iClkFast);
            $display("Time: %0t | Valid In: %b | Data In: %3d || Valid Out: %b | Data Out: %4d", 
                     $time, iValidIn, iDataIn, oValidOut, oDataOut);
        end

        $display("----------------------------------------");
        $display("Test 4: Flushing the filter (Zeros)");
        $display("----------------------------------------");
        for (Idx = 0; Idx < 4; Idx = Idx + 1) begin
            iDataIn = 0;
            @(negedge iClkFast);
            $display("Time: %0t | Valid In: %b | Data In: %3d || Valid Out: %b | Data Out: %4d", 
                     $time, iValidIn, iDataIn, oValidOut, oDataOut);
        end
        
        iValidIn = 0; // End of stream

        #50;
        $display("----------------------------------------");
        $display("Testbench Completed Successfully!");
        $display("----------------------------------------");
        $finish;
    end

endmodule

FPGA_FIR_Filter/fir_waves.vcd
$date
	Sun Jun 21 23:10:16 2026
$end
$version
	Icarus Verilog
$end
$timescale
	1ps
$end
$scope module FIR_Filter_TB $end
$var wire 1 ! oValidOut $end
$var wire 16 " oDataOut [15:0] $end
$var reg 1 # iClkFast $end
$var reg 8 $ iDataIn [7:0] $end
$var reg 1 % iRstN $end
$var reg 1 & iValidIn $end
$var integer 32 ' Idx [31:0] $end
$scope module uut $end
$var wire 1 # iClkFast $end
$var wire 8 ( iDataIn [7:0] $end
$var wire 1 % iRstN $end
$var wire 1 & iValidIn $end
$var wire 16 ) wTerm0 [15:0] $end
$var wire 16 * wX3 [15:0] $end
$var wire 16 + wX2 [15:0] $end
$var wire 16 , wX1 [15:0] $end
$var wire 16 - wX0 [15:0] $end
$var wire 16 . wTerm3 [15:0] $end
$var wire 16 / wTerm2 [15:0] $end
$var wire 16 0 wTerm1 [15:0] $end
$var wire 16 1 wNextSum [15:0] $end
$var reg 16 2 oDataOut [15:0] $end
$var reg 1 ! oValidOut $end
$var reg 8 3 rX0 [7:0] $end
$var reg 8 4 rX1 [7:0] $end
$var reg 8 5 rX2 [7:0] $end
$var reg 8 6 rX3 [7:0] $end
$upscope $end
$upscope $end
$enddefinitions $end
$comment Show the parameter values. $end
$dumpall
$end
#0
$dumpvars
b0 6
b0 5
b0 4
b0 3
b0 2
b0 1
b0 0
b0 /
b0 .
b0 -
b0 ,
b0 +
b0 *
b0 )
b0 (
bx '
0&
0%
b0 $
0#
b0 "
0!
$end
#5000
1#
#10000
0#
#15000
1#
#20000
0#
1%
#25000
1#
#30000
0#
#35000
1#
#40000
b1010 1
b1010 )
b1010 -
b1010 $
b1010 (
b1 '
1&
0#
#45000
b11110 1
b10100 0
b1010 "
b1010 2
b1010 ,
b1010 3
1!
1#
#50000
b101000 1
b10100 )
b10100 -
b10100 $
b10100 (
b10 '
0#
#55000
b101000 0
b101000 "
b101000 2
b1011010 1
b11110 /
b1010 +
b1010 4
b10100 ,
b10100 3
1#
#60000
b1100100 1
b11110 )
b11110 -
b11110 $
b11110 (
b11 '
0#
#65000
b101000 .
b111100 0
b1100100 "
b1100100 2
b1010 *
b1010 5
b10111110 1
b111100 /
b10100 +
b10100 4
b11110 ,
b11110 3
1#
#70000
b11001000 1
b101000 )
b101000 -
b101000 $
b101000 (
b100 '
0#
#75000
b1010000 .
b1010000 0
b11001000 "
b11001000 2
b1010 6
b10100 *
b10100 5
b100100010 1
b1011010 /
b11110 +
b11110 4
b101000 ,
b101000 3
1#
#80000
b100101100 1
b110010 )
b110010 -
b110010 $
b110010 (
b101 '
0#
#85000
b1111000 .
b1100100 0
b100101100 "
b100101100 2
b10100 6
b11110 *
b11110 5
b110000110 1
b1111000 /
b101000 +
b101000 4
b110010 ,
b110010 3
1#
#90000
b110110111 1
b1100011 )
b1100011 -
b1100011 $
b1100011 (
0&
b0 '
0#
#95000
0!
1#
#100000
b1 '
0#
#105000
1#
#110000
b10 '
0#
#115000
1#
#120000
b101011110 1
b1010 )
b1010 -
b1010 $
b1010 (
1&
b0 '
0#
#125000
b10100000 .
b10100 0
b101011110 "
b101011110 2
b11110 6
b101000 *
b101000 5
b101010100 1
b10010110 /
b110010 +
b110010 4
b1010 ,
b1010 3
1!
1#
#130000
b1 '
0#
#135000
b11001000 .
b101010100 "
b101010100 2
b101000 6
b110010 *
b110010 5
b100000100 1
b11110 /
b1010 +
b1010 4
1#
#140000
b10 '
0#
#145000
b1100100 1
b101000 .
b100000100 "
b100000100 2
b110010 6
b1010 *
b1010 5
1#
#150000
b11 '
0#
#155000
b1100100 "
b1100100 2
b1010 6
1#
#160000
b100 '
0#
#165000
1#
#170000
b1011010 1
b0 )
b0 -
b0 $
b0 (
b0 '
0#
#175000
b1000110 1
b0 0
b1011010 "
b1011010 2
b0 ,
b0 3
1#
#180000
b1 '
0#
#185000
b1000110 "
b1000110 2
b101000 1
b0 /
b0 +
b0 4
1#
#190000
b10 '
0#
#195000
b0 1
b0 .
b101000 "
b101000 2
b0 *
b0 5
1#
#200000
b11 '
0#
#205000
b0 "
b0 2
b0 6
1#
#210000
0&
b100 '
0#
#215000
0!
1#
#220000
0#
#225000
1#
#230000
0#
#235000
1#
#240000
0#
#245000
1#
#250000
0#
#255000
1#
#260000
0#
