FPGA_Clk_Div/rtl/Baud_Clk_Divider_50.v
//============================================================
// Module Name : Baud_Clk_Divider_50
// Description : 50% duty-cycle clock divider for UART baud clock
//
// Function:
//   - Divides the input clock by 2*HALF_DIV.
//   - Output clock toggles every HALF_DIV input clock cycles.
//   - Uses a down-counter.
//   - Terminal count is detected using only ONE BIT:
//       wCntDec[CNT_W]
//     This bit becomes '1' when the counter underflows.
//
// Example:
//   If input clock = 10 MHz
//   HALF_DIV = 520
//
//   Output frequency:
//       Fout = 10 MHz / (2 * 520)
//            = 9615.38 Hz
//
// Notes:
//   - For a real 9600 baud UART from 10 MHz, exact integer division
//     is not possible.
//   - This divider gives a close baud clock with 50% duty cycle.
//============================================================

module Baud_Clk_Divider_50
#(
    parameter HALF_DIV = 520
)
(
    input  wire iClk,       // Input clock, for example slow_clk = 10 MHz
    input  wire iResetN,    // Asynchronous active-low reset
    output reg  oClk        // Divided output clock, 50% duty cycle
);

    //--------------------------------------------------------
    // Counter width calculation
    //
    // HALF_DIV+1 is used so the counter has enough bits
    // to hold the reload value and also detect underflow.
    //--------------------------------------------------------
    localparam CNT_W = $clog2(HALF_DIV + 1);

    //--------------------------------------------------------
    // Counter register
    //
    // rCnt is declared with one extra bit:
    //   [CNT_W:0]
    //
    // The extra MSB is used as the underflow indication bit.
    //--------------------------------------------------------
    reg [CNT_W:0] rCnt;

    //--------------------------------------------------------
    // Decremented counter value
    //
    // This wire calculates rCnt - 1 before loading the register.
    // The MSB of this result is used to detect underflow.
    //
    // This avoids using a wide comparator such as:
    //   if (rCnt == 0)
    //
    // Instead, only one bit is checked:
    //   if (wCntDec[CNT_W])
    //--------------------------------------------------------
    wire [CNT_W:0] wCntDec;

    assign wCntDec = rCnt - 1'b1;

    //--------------------------------------------------------
    // Clock divider logic
    //
    // Reset:
    //   - Load the counter with HALF_DIV-1.
    //   - Drive output clock low.
    //
    // Normal operation:
    //   - Counter counts down.
    //   - When underflow is detected, reload counter and toggle oClk.
    //--------------------------------------------------------
    always @(posedge iClk or negedge iResetN) begin
        if (!iResetN) begin
            rCnt <= HALF_DIV - 1'b1;
            oClk <= 1'b0;
        end
        else begin
            if (wCntDec[CNT_W]) begin
                rCnt <= HALF_DIV - 1'b1;
                oClk <= ~oClk;
            end
            else begin
                rCnt <= wCntDec;
            end
        end
    end

endmodule

FPGA_Clk_Div/rtl/TB_Baud_Clk_Divider_50.v
`timescale 1ns/1ps

//============================================================
// Testbench Name : TB_Baud_Clk_Divider_50
// Description    : Testbench for Baud_Clk_Divider_50
//
// Test purpose:
//   - Generate a 10 MHz input clock.
//   - Apply reset.
//   - Verify that oClk toggles every HALF_DIV input cycles.
//   - Verify 50% duty-cycle behavior.
//
// Simulation note:
//   - HALF_DIV is set to 5 for fast simulation.
//   - In the real project, use HALF_DIV = 520.
//============================================================

module TB_Baud_Clk_Divider_50;

    //--------------------------------------------------------
    // Testbench signals
    //--------------------------------------------------------
    reg  iClk;
    reg  iResetN;
    wire oClk;

    //--------------------------------------------------------
    // DUT instantiation
    //
    // HALF_DIV = 5 only for simulation speed.
    // Real value for 10 MHz to approximately 9600 baud:
    //   HALF_DIV = 520
    //--------------------------------------------------------
    Baud_Clk_Divider_50
    #(
        .HALF_DIV(5)
    )
    dut
    (
        .iClk    (iClk),
        .iResetN (iResetN),
        .oClk    (oClk)
    );

    //--------------------------------------------------------
    // Input clock generation
    //
    // Period = 100 ns
    // Frequency = 10 MHz
    //--------------------------------------------------------
    initial begin
        iClk = 1'b0;
        forever #50 iClk = ~iClk;
    end

    //--------------------------------------------------------
    // Main stimulus
    //--------------------------------------------------------
    initial begin

        //----------------------------------------------------
        // Dump signals to VCD file for waveform viewing
        //----------------------------------------------------
        $dumpfile("TB_Baud_Clk_Divider_50.vcd");
        $dumpvars(0, TB_Baud_Clk_Divider_50);

        //----------------------------------------------------
        // Apply reset
        //----------------------------------------------------
        iResetN = 1'b0;

        repeat(4) @(posedge iClk);

        //----------------------------------------------------
        // Release reset
        //----------------------------------------------------
        iResetN = 1'b1;

        //----------------------------------------------------
        // Run long enough to observe multiple output periods
        //----------------------------------------------------
        repeat(100) @(posedge iClk);

        //----------------------------------------------------
        // End simulation
        //----------------------------------------------------
        $finish;
    end

endmodule

FPGA_Clk_Div/sim/TB_Baud_Clk_Divider_50.vcd
$date
	Fri Jun 26 14:35:58 2026
$end
$version
	ModelSim Version 2020.1
$end
$timescale
	1ps
$end

$scope module TB_Baud_Clk_Divider_50 $end
$var reg 1 ! iClk $end
$var reg 1 " iResetN $end
$var wire 1 # oClk $end

$scope module dut $end
$var parameter 32 $ HALF_DIV $end
$var parameter 32 % CNT_W $end
$var wire 1 & iClk $end
$var wire 1 ' iResetN $end
$var reg 1 ( oClk $end
$var reg 4 ) rCnt [3:0] $end
$var wire 1 * wCntDec [3] $end
$var wire 1 + wCntDec [2] $end
$var wire 1 , wCntDec [1] $end
$var wire 1 - wCntDec [0] $end
$upscope $end
$upscope $end
$enddefinitions $end
#0
$dumpvars
0!
0"
0(
b100 )
b101 $
b11 %
0#
1-
1,
0+
0*
0'
0&
$end
#50000
1!
1&
#100000
0!
0&
#150000
1!
1&
#200000
0!
0&
#250000
1!
1&
#300000
0!
0&
#350000
1!
1&
1"
1'
#400000
0!
0&
#450000
1!
1&
b11 )
0-
#500000
0!
0&
#550000
1!
1&
b10 )
1-
0,
#600000
0!
0&
#650000
1!
1&
b1 )
0-
#700000
0!
0&
#750000
1!
1&
b0 )
1-
1,
1+
1*
#800000
0!
0&
#850000
1!
1&
b100 )
1(
0+
0*
1#
#900000
0!
0&
#950000
1!
1&
b11 )
0-
#1000000
0!
0&
#1050000
1!
1&
b10 )
1-
0,
#1100000
0!
0&
#1150000
1!
1&
b1 )
0-
#1200000
0!
0&
#1250000
1!
1&
b0 )
1-
1,
1+
1*
#1300000
0!
0&
#1350000
1!
1&
b100 )
0(
0+
0*
0#
#1400000
0!
0&
#1450000
1!
1&
b11 )
0-
#1500000
0!
0&
#1550000
1!
1&
b10 )
1-
0,
#1600000
0!
0&
#1650000
1!
1&
b1 )
0-
#1700000
0!
0&
#1750000
1!
1&
b0 )
1-
1,
1+
1*
#1800000
0!
0&
#1850000
1!
1&
b100 )
1(
0+
0*
1#
#1900000
0!
0&
#1950000
1!
1&
b11 )
0-
#2000000
0!
0&
#2050000
1!
1&
b10 )
1-
0,
#2100000
0!
0&
#2150000
1!
1&
b1 )
0-
#2200000
0!
0&
#2250000
1!
1&
b0 )
1-
1,
1+
1*
#2300000
0!
0&
#2350000
1!
1&
b100 )
0(
0+
0*
0#
#2400000
0!
0&
#2450000
1!
1&
b11 )
0-
#2500000
0!
0&
#2550000
1!
1&
b10 )
1-
0,
#2600000
0!
0&
#2650000
1!
1&
b1 )
0-
#2700000
0!
0&
#2750000
1!
1&
b0 )
1-
1,
1+
1*
#2800000
0!
0&
#2850000
1!
1&
b100 )
1(
0+
0*
1#
#2900000
0!
0&
#2950000
1!
1&
b11 )
0-
#3000000
0!
0&
#3050000
1!
1&
b10 )
1-
0,
#3100000
0!
0&
#3150000
1!
1&
b1 )
0-
#3200000
0!
0&
#3250000
1!
1&
b0 )
1-
1,
1+
1*
#3300000
0!
0&
#3350000
1!
1&
b100 )
0(
0+
0*
0#
#3400000
0!
0&
#3450000
1!
1&
b11 )
0-
#3500000
0!
0&
#3550000
1!
1&
b10 )
1-
0,
#3600000
0!
0&
#3650000
1!
1&
b1 )
0-
#3700000
0!
0&
#3750000
1!
1&
b0 )
1-
1,
1+
1*
#3800000
0!
0&
#3850000
1!
1&
b100 )
1(
0+
0*
1#
#3900000
0!
0&
#3950000
1!
1&
b11 )
0-
#4000000
0!
0&
#4050000
1!
1&
b10 )
1-
0,
#4100000
0!
0&
#4150000
1!
1&
b1 )
0-
#4200000
0!
0&
#4250000
1!
1&
b0 )
1-
1,
1+
1*
#4300000
0!
0&
#4350000
1!
1&
b100 )
0(
0+
0*
0#
#4400000
0!
0&
#4450000
1!
1&
b11 )
0-
#4500000
0!
0&
#4550000
1!
1&
b10 )
1-
0,
#4600000
0!
0&
#4650000
1!
1&
b1 )
0-
#4700000
0!
0&
#4750000
1!
1&
b0 )
1-
1,
1+
1*
#4800000
0!
0&
#4850000
1!
1&
b100 )
1(
0+
0*
1#
#4900000
0!
0&
#4950000
1!
1&
b11 )
0-
#5000000
0!
0&
#5050000
1!
1&
b10 )
1-
0,
#5100000
0!
0&
#5150000
1!
1&
b1 )
0-
#5200000
0!
0&
#5250000
1!
1&
b0 )
1-
1,
1+
1*
#5300000
0!
0&
#5350000
1!
1&
b100 )
0(
0+
0*
0#
#5400000
0!
0&
#5450000
1!
1&
b11 )
0-
#5500000
0!
0&
#5550000
1!
1&
b10 )
1-
0,
#5600000
0!
0&
#5650000
1!
1&
b1 )
0-
#5700000
0!
0&
#5750000
1!
1&
b0 )
1-
1,
1+
1*
#5800000
0!
0&
#5850000
1!
1&
b100 )
1(
0+
0*
1#
#5900000
0!
0&
#5950000
1!
1&
b11 )
0-
#6000000
0!
0&
#6050000
1!
1&
b10 )
1-
0,
#6100000
0!
0&
#6150000
1!
1&
b1 )
0-
#6200000
0!
0&
#6250000
1!
1&
b0 )
1-
1,
1+
1*
#6300000
0!
0&
#6350000
1!
1&
b100 )
0(
0+
0*
0#
#6400000
0!
0&
#6450000
1!
1&
b11 )
0-
#6500000
0!
0&
#6550000
1!
1&
b10 )
1-
0,
#6600000
0!
0&
#6650000
1!
1&
b1 )
0-
#6700000
0!
0&
#6750000
1!
1&
b0 )
1-
1,
1+
1*
#6800000
0!
0&
#6850000
1!
1&
b100 )
1(
0+
0*
1#
#6900000
0!
0&
#6950000
1!
1&
b11 )
0-
#7000000
0!
0&
#7050000
1!
1&
b10 )
1-
0,
#7100000
0!
0&
#7150000
1!
1&
b1 )
0-
#7200000
0!
0&
#7250000
1!
1&
b0 )
1-
1,
1+
1*
#7300000
0!
0&
#7350000
1!
1&
b100 )
0(
0+
0*
0#
#7400000
0!
0&
#7450000
1!
1&
b11 )
0-
#7500000
0!
0&
#7550000
1!
1&
b10 )
1-
0,
#7600000
0!
0&
#7650000
1!
1&
b1 )
0-
#7700000
0!
0&
#7750000
1!
1&
b0 )
1-
1,
1+
1*
#7800000
0!
0&
#7850000
1!
1&
b100 )
1(
0+
0*
1#
#7900000
0!
0&
#7950000
1!
1&
b11 )
0-
#8000000
0!
0&
#8050000
1!
1&
b10 )
1-
0,
#8100000
0!
0&
#8150000
1!
1&
b1 )
0-
#8200000
0!
0&
#8250000
1!
1&
b0 )
1-
1,
1+
1*
#8300000
0!
0&
#8350000
1!
1&
b100 )
0(
0+
0*
0#
#8400000
0!
0&
#8450000
1!
1&
b11 )
0-
#8500000
0!
0&
#8550000
1!
1&
b10 )
1-
0,
#8600000
0!
0&
#8650000
1!
1&
b1 )
0-
#8700000
0!
0&
#8750000
1!
1&
b0 )
1-
1,
1+
1*
#8800000
0!
0&
#8850000
1!
1&
b100 )
1(
0+
0*
1#
#8900000
0!
0&
#8950000
1!
1&
b11 )
0-
#9000000
0!
0&
#9050000
1!
1&
b10 )
1-
0,
#9100000
0!
0&
#9150000
1!
1&
b1 )
0-
#9200000
0!
0&
#9250000
1!
1&
b0 )
1-
1,
1+
1*
#9300000
0!
0&
#9350000
1!
1&
b100 )
0(
0+
0*
0#
#9400000
0!
0&
#9450000
1!
1&
b11 )
0-
#9500000
0!
0&
#9550000
1!
1&
b10 )
1-
0,
#9600000
0!
0&
#9650000
1!
1&
b1 )
0-
#9700000
0!
0&
#9750000
1!
1&
b0 )
1-
1,
1+
1*
#9800000
0!
0&
#9850000
1!
1&
b100 )
1(
0+
0*
1#
#9900000
0!
0&
#9950000
1!
1&
b11 )
0-
#10000000
0!
0&
#10050000
1!
1&
b10 )
1-
0,
#10100000
0!
0&
#10150000
1!
1&
b1 )
0-
#10200000
0!
0&
#10250000
1!
1&
b0 )
1-
1,
1+
1*
